{"is_source_file": true, "format": "TypeScript", "description": "This file defines a React functional component called Sidebar, serving as a placeholder for sidebar navigation elements, likely to include future categories, tags, or filters.", "external_files": ["react"], "external_methods": [], "published": ["Sidebar"], "classes": [], "methods": ["Sidebar"], "calls": [], "search-terms": ["Sidebar", "React", "component", "navigation", "placeholder", "categories", "tags"], "state": 2, "file_id": 16, "knowledge_revision": 56, "git_revision": "", "revision_history": [{"47": ""}, {"56": ""}], "ctags": [], "hash": "ba0a4c0b723c6191f4e18f7041f0895c", "format-version": 4, "code-base-name": "notes_frontend", "filename": "notes_frontend/src/components/Sidebar.tsx"}